Metadata-Version: 2.1
Name: distributionAnggi
Version: 0.1
Summary: Gaussian distributions
